deletion_records/__init__.py
deletion_records/admin.py
deletion_records/apps.py
deletion_records/models.py
deletion_records/py.typed
deletion_records/management/commands/__init__.py
deletion_records/management/commands/deletion_migration_operations.py
deletion_records/migrations/0001_initial.py
deletion_records/migrations/__init__.py
django_deletion_records-0.2.0.dist-info/METADATA
django_deletion_records-0.2.0.dist-info/WHEEL
django_deletion_records-0.2.0.dist-info/licenses/LICENSE
django_deletion_records-0.2.0.dist-info/RECORD
