Metadata-Version: 2.1
Name: django-deletion-records
Version: 0.2.0
Summary: A Django application to track deleted records.
Project-URL: Homepage, https://github.com/realsuayip/django-deletion-records
Project-URL: Bug Tracker, https://github.com/realsuayip/django-deletion-records/issues
Author-email: suayip uzulmez <suayip.541@gmail.com>
License: Copyright (c) 2024, Şuayip Üzülmez
License-File: LICENSE
Keywords: django,soft-delete
Classifier: License :: OSI Approved :: BSD License
Classifier: Programming Language :: Python
Classifier: Programming Language :: Python :: 3
Requires-Python: >=3.10
Requires-Dist: django>=3.2
